stringtools/__init__.py
stringtools/analysers.py
stringtools/converters.py
stringtools/general.py
stringtools/generators.py
stringtools/validators.py
stringtools/languages/de.txt
stringtools/languages/en.txt
stringtools/languages/fr.txt
stringtools/languages/ru.txt
tests/__init__.py
tests/test_.py
tests/test_stringtools_version_name.py
stringtools-3.0.1.dist-info/LICENSE
stringtools-3.0.1.dist-info/METADATA
stringtools-3.0.1.dist-info/WHEEL
stringtools-3.0.1.dist-info/top_level.txt
stringtools-3.0.1.dist-info/RECORD
